llama_index/retrievers/galaxia/__init__.py
llama_index/retrievers/galaxia/base.py
llama_index_retrievers_galaxia-0.2.1.dist-info/METADATA
llama_index_retrievers_galaxia-0.2.1.dist-info/WHEEL
llama_index_retrievers_galaxia-0.2.1.dist-info/RECORD
