Metadata-Version: 2.4
Name: llama-index-retrievers-galaxia
Version: 0.2.1
Summary: llama-index retrievers galaxia integration
Author: Robert Rozanski
License-Expression: MIT
Requires-Python: <4.0,>=3.8.1
Requires-Dist: llama-index-core<0.13,>=0.10.0
